newtonMethod/__init__.py
newtonMethod/newton.py
newtonMethod/test.py
newtonMethod/test1.py
newtonMethod-0.1.dist-info/LICENSE
newtonMethod-0.1.dist-info/METADATA
newtonMethod-0.1.dist-info/WHEEL
newtonMethod-0.1.dist-info/top_level.txt
newtonMethod-0.1.dist-info/RECORD
