Metadata-Version: 2.1
Name: newtonMethod
Version: 0.1
Summary: Package to find a good approximation for the root of a real-valued function f(x)=0
Home-page: https://github.com/es-g/newtonMethod
Author: Yesbol Gabdullin
Author-email: yesbol_gabdullin@hotmail.com
License: UNKNOWN
Platform: UNKNOWN
Classifier: Programming Language :: Python :: 3
Classifier: License :: OSI Approved :: MIT License
Classifier: Operating System :: OS Independent
